st7_wrap/St7API.py
st7_wrap/__init__.py
st7_wrap/arrays.py
st7_wrap/const.py
st7_wrap/exc.py
st7_wrap/st7.py
st7_wrap-0.0.2.dist-info/LICENSE
st7_wrap-0.0.2.dist-info/METADATA
st7_wrap-0.0.2.dist-info/WHEEL
st7_wrap-0.0.2.dist-info/top_level.txt
st7_wrap-0.0.2.dist-info/RECORD
