Metadata-Version: 2.1
Name: st7_wrap
Version: 0.0.2
Summary: Wrapper for the Strand7 API
Home-page: https://github.com/tom-dq/st7_wrap
Author: Tom Wilson
Author-email: tom.wilson.66+st7_wrap@gmail.com
License: UNKNOWN
Project-URL: Bug Tracker, https://github.com/tom-dq/st7_wrap/issues
Platform: UNKNOWN
Classifier: Development Status :: 3 - Alpha
Classifier: Programming Language :: Python :: 3
Classifier: Programming Language :: Python :: 3.7
Classifier: Programming Language :: Python :: 3.8
Classifier: Programming Language :: Python :: 3.9
Classifier: License :: OSI Approved :: MIT License
Classifier: Operating System :: Microsoft :: Windows
Requires-Python: >=3.7
License-File: LICENSE
